quantulum3/__init__.py
quantulum3/classes.py
quantulum3/classifier.py
quantulum3/disambiguate.py
quantulum3/entities.json
quantulum3/language.py
quantulum3/load.py
quantulum3/no_classifier.py
quantulum3/parser.py
quantulum3/regex.py
quantulum3/speak.py
quantulum3/units.json
quantulum3/_lang/__init__.py
quantulum3/_lang/en_US/__init__.py
quantulum3/_lang/en_US/classifier.py
quantulum3/_lang/en_US/clf.joblib
quantulum3/_lang/en_US/common-words.json
quantulum3/_lang/en_US/entities.json
quantulum3/_lang/en_US/load.py
quantulum3/_lang/en_US/parser.py
quantulum3/_lang/en_US/regex.py
quantulum3/_lang/en_US/speak.py
quantulum3/_lang/en_US/units.json
quantulum3/_lang/en_US/tests/__init__.py
quantulum3/_lang/en_US/tests/errors.json
quantulum3/_lang/en_US/tests/expand.json
quantulum3/_lang/en_US/tests/extract_spellout_values.py
quantulum3/_lang/en_US/tests/quantities.ambiguity.json
quantulum3/_lang/en_US/tests/quantities.json
quantulum3/_lang/en_US/train/__init__.py
quantulum3/_lang/en_US/train/similars.json
quantulum3/_lang/en_US/train/train.json
quantulum3/_lang/en_US/train/wiki.json
quantulum3/scripts/__init__.py
quantulum3/scripts/train.py
quantulum3/tests/__init__.py
quantulum3/tests/test_classes.py
quantulum3/tests/test_classifier.py
quantulum3/tests/test_hypothesis.py
quantulum3/tests/test_load.py
quantulum3/tests/test_no_classifier.py
quantulum3/tests/test_parse_ranges.py
quantulum3/tests/test_scripts.py
quantulum3/tests/test_setup.py
quantulum3-0.9.2.dist-info/AUTHORS
quantulum3-0.9.2.dist-info/LICENSE
quantulum3-0.9.2.dist-info/METADATA
quantulum3-0.9.2.dist-info/WHEEL
quantulum3-0.9.2.dist-info/entry_points.txt
quantulum3-0.9.2.dist-info/top_level.txt
quantulum3-0.9.2.dist-info/RECORD
