Metadata-Version: 2.1
Name: quantulum3
Version: 0.9.2
Summary: Extract quantities from unstructured text.
Home-page: https://github.com/nielstron/quantulum3
Download-URL: https://github.com/nielstron/quantulum3/tarball/master
Author: Marco Lagi, nielstron, sohrabtowfighi, grhawk and Rodrigo Castro
Author-email: n.muendler@web.de
License: MIT
Keywords: information extraction,quantities,units,measurements,nlp,natural language processing,text mining,text processing
Classifier: Intended Audience :: Developers
Classifier: Intended Audience :: Science/Research
Classifier: Operating System :: MacOS :: MacOS X
Classifier: Operating System :: Microsoft :: Windows
Classifier: Operating System :: POSIX
Classifier: License :: OSI Approved :: MIT License
Classifier: Programming Language :: Python
Classifier: Programming Language :: Python :: 3.8
Classifier: Programming Language :: Python :: 3.9
Classifier: Programming Language :: Python :: 3.10
Classifier: Programming Language :: Python :: 3.11
Classifier: Development Status :: 3 - Alpha
Classifier: Natural Language :: English
Classifier: Topic :: Text Processing :: Linguistic
Classifier: Topic :: Scientific/Engineering
License-File: LICENSE
License-File: AUTHORS
Requires-Dist: inflect
Requires-Dist: num2words
Provides-Extra: classifier
Requires-Dist: numpy; extra == "classifier"
Requires-Dist: scipy; extra == "classifier"
Requires-Dist: scikit-learn; extra == "classifier"
Requires-Dist: joblib; extra == "classifier"
Requires-Dist: wikipedia; extra == "classifier"
Requires-Dist: stemming; extra == "classifier"
